aiogram_blueprint/__init__.py
aiogram_blueprint/__main__.py
aiogram_blueprint/constants.py
aiogram_blueprint/generator.py
aiogram_blueprint/survey.py
aiogram_blueprint/utils.py
aiogram_blueprint/template/.env.j2
aiogram_blueprint/template/Dockerfile
aiogram_blueprint/template/alembic.ini
aiogram_blueprint/template/docker-compose.yml
aiogram_blueprint/template/requirements.txt.j2
aiogram_blueprint/template/alembic/README
aiogram_blueprint/template/alembic/env.py
aiogram_blueprint/template/alembic/env.py.j2
aiogram_blueprint/template/alembic/script.py.mako
aiogram_blueprint/template/alembic/versions/.gitkeep
aiogram_blueprint/template/data/.gitkeep
aiogram_blueprint/template/locales/en.yaml
aiogram_blueprint/template/project/__init__.py
aiogram_blueprint/template/project/__main__.py
aiogram_blueprint/template/project/__main__.py.j2
aiogram_blueprint/template/project/config.py
aiogram_blueprint/template/project/config.py.j2
aiogram_blueprint/template/project/context.py
aiogram_blueprint/template/project/context.py.j2
aiogram_blueprint/template/project/app/__init__.py
aiogram_blueprint/template/project/app/admin/__init__.py
aiogram_blueprint/template/project/app/routes/__init__.py
aiogram_blueprint/template/project/app/routes/bot_update.py
aiogram_blueprint/template/project/bot/__init__.py
aiogram_blueprint/template/project/bot/commands.py
aiogram_blueprint/template/project/bot/filters/__init__.py
aiogram_blueprint/template/project/bot/filters/is_admin.py
aiogram_blueprint/template/project/bot/filters/is_admin.py.j2
aiogram_blueprint/template/project/bot/handlers/__init__.py
aiogram_blueprint/template/project/bot/handlers/commands.py
aiogram_blueprint/template/project/bot/handlers/common.py
aiogram_blueprint/template/project/bot/handlers/errors.py
aiogram_blueprint/template/project/bot/middlewares/__init__.py
aiogram_blueprint/template/project/bot/middlewares/__init__.py.j2
aiogram_blueprint/template/project/bot/middlewares/db.py
aiogram_blueprint-0.0.0b14.dist-info/licenses/LICENSE
aiogram_blueprint-0.0.0b14.dist-info/METADATA
aiogram_blueprint-0.0.0b14.dist-info/WHEEL
aiogram_blueprint-0.0.0b14.dist-info/entry_points.txt
aiogram_blueprint-0.0.0b14.dist-info/top_level.txt
aiogram_blueprint-0.0.0b14.dist-info/RECORD
