Metadata-Version: 2.4
Name: aiogram-blueprint
Version: 0.0.0b14
License-File: LICENSE
Requires-Dist: click~=8.2.1
Requires-Dist: Jinja2~=3.1.6
Requires-Dist: InquirerPy~=0.3.4
Dynamic: license-file
Dynamic: requires-dist
